devman/__init__.py
devman/__main__.py
devman/cli.py
devman/config.py
devman/exitcodes.py
devman/podman.py
devman-0.1.6.dist-info/METADATA
devman-0.1.6.dist-info/WHEEL
devman-0.1.6.dist-info/entry_points.txt
devman-0.1.6.dist-info/licenses/LICENSE
devman-0.1.6.dist-info/RECORD
